inverse_covariance/rank_correlation.py
inverse_covariance/adaptive_graph_lasso.py
inverse_covariance/model_average.py
inverse_covariance/__init__.py
inverse_covariance/plot_util.py
inverse_covariance/quic_graph_lasso.py
inverse_covariance/inverse_covariance.py
inverse_covariance/metrics.py
inverse_covariance/profiling/erdos_renyi_graph.py
inverse_covariance/profiling/__init__.py
inverse_covariance/profiling/monte_carlo_profile.py
inverse_covariance/profiling/lattice_graph.py
inverse_covariance/profiling/cluster_graph.py
inverse_covariance/profiling/graphs.py
inverse_covariance/profiling/metrics.py
inverse_covariance/pyquic/__init__.py
inverse_covariance/pyquic/setup.py
inverse_covariance/pyquic/pyquic.cpython-39-x86_64-linux-gnu.so
skggm2.libs/liblapack-1ad85175.so.3.4.2
skggm2.libs/libquadmath-96973f99.so.0.0.0
skggm2.libs/libgfortran-91cc3cb1.so.3.0.0
skggm2.libs/libblas-357956a1.so.3.4.2
skggm2-0.2.10.dist-info/LICENSE
skggm2-0.2.10.dist-info/WHEEL
skggm2-0.2.10.dist-info/top_level.txt
skggm2-0.2.10.dist-info/RECORD
skggm2-0.2.10.dist-info/METADATA
